condor_kmeans/__init__.py
condor_kmeans/condor.py
condor_kmeans/kmeans.py
condor_kmeans/utils.py
condor_kmeans/vector.py
condor_kmeans-0.9.dist-info/DESCRIPTION.rst
condor_kmeans-0.9.dist-info/METADATA
condor_kmeans-0.9.dist-info/RECORD
condor_kmeans-0.9.dist-info/WHEEL
condor_kmeans-0.9.dist-info/entry_points.txt
condor_kmeans-0.9.dist-info/metadata.json
condor_kmeans-0.9.dist-info/top_level.txt
