Metadata-Version: 2.0
Name: condor-kmeans
Version: 0.9
Summary: A package for running k-means on a Condor cluster
Home-page: https://github.com/tansey/condor-kmeans
Author: Wesley Tansey
Author-email: wes.tansey@gmail.com
License: MIT
Keywords: statistics machinelearning clustering kmeans condor
Platform: UNKNOWN
Classifier: Development Status :: 3 - Alpha
Classifier: Intended Audience :: Science/Research
Classifier: Topic :: Scientific/Engineering
Classifier: License :: OSI Approved :: GNU Lesser General Public License v3 or later (LGPLv3+)
Classifier: Programming Language :: Python :: 2
Classifier: Programming Language :: Python :: 2.7
Requires-Dist: numpy
